vue/__init__.py
vue/__version__.py
vue/factory.py
vue/router.py
vue/store.py
vue/utils.py
vue/vue.py
vue/bridge/__init__.py
vue/bridge/dict.py
vue/bridge/list.py
vue/bridge/object.py
vue/bridge/vue_instance.py
vue/bridge/vuex_instance.py
vue/decorators/__init__.py
vue/decorators/action.py
vue/decorators/base.py
vue/decorators/components.py
vue/decorators/computed.py
vue/decorators/custom.py
vue/decorators/data.py
vue/decorators/directive.py
vue/decorators/extends.py
vue/decorators/filters.py
vue/decorators/getter.py
vue/decorators/lifecycle_hook.py
vue/decorators/method.py
vue/decorators/mixins.py
vue/decorators/model.py
vue/decorators/mutation.py
vue/decorators/plugin.py
vue/decorators/prop.py
vue/decorators/render.py
vue/decorators/routes.py
vue/decorators/state.py
vue/decorators/template.py
vue/decorators/watcher.py
vuecli/__init__.py
vuecli/cli.py
vuecli/index.html
vuecli/loading.gif
vuecli/js/LICENSE_VUE
vuecli/js/LICENSE_VUEX
vuecli/js/LICENSE_VUE_ROUTER
vuecli/js/vue-router.js
vuecli/js/vue.js
vuecli/js/vuex.js
vuecli/provider/__init__.py
vuecli/provider/flask.py
vuecli/provider/provider.py
vuecli/provider/static.py
vuepy-0.3.0.dist-info/LICENSE
vuepy-0.3.0.dist-info/METADATA
vuepy-0.3.0.dist-info/WHEEL
vuepy-0.3.0.dist-info/entry_points.txt
vuepy-0.3.0.dist-info/top_level.txt
vuepy-0.3.0.dist-info/RECORD
