Metadata-Version: 2.1
Name: vuepy
Version: 0.3.0
Summary: Pythonic Vue
Home-page: https://stefanhoelzl.github.io/vue.py/
Author: Stefan Hoelzl
Author-email: stefan.hoelzl@posteo.de
License: MIT
Keywords: web reactive gui framework
Platform: UNKNOWN
Classifier: Development Status :: 4 - Beta
Classifier: Environment :: Web Environment
Classifier: Intended Audience :: Developers
Classifier: License :: OSI Approved :: MIT License
Classifier: Programming Language :: Python :: 3
Classifier: Programming Language :: Python :: 3.6
Classifier: Operating System :: MacOS :: MacOS X
Classifier: Operating System :: POSIX :: Linux
Classifier: Operating System :: Microsoft :: Windows
Classifier: Topic :: Internet :: WWW/HTTP
Classifier: Topic :: Software Development
Classifier: Topic :: Software Development :: Libraries :: Application Frameworks
Requires-Dist: brython (==3.8.9)
Requires-Dist: Jinja2 (~=2.10)
Requires-Dist: pyyaml (~=5.1)
Provides-Extra: flask
Requires-Dist: Flask (~=1.0) ; extra == 'flask'
